maglevai/__init__.py
maglevai-0.1.5.dist-info/METADATA
maglevai-0.1.5.dist-info/WHEEL
maglevai-0.1.5.dist-info/RECORD
