Metadata-Version: 2.1
Name: maglevai
Version: 0.1.5
Summary: Making AI content safe and trustworthy
Home-page: https://github.com/Maglev-AI/MaglevAI
Author: Maglev AI, Inc.
Author-email: 97685959+MaglevAIInc@users.noreply.github.com
Requires-Python: >=3.8,<4.0
Classifier: Programming Language :: Python :: 3
Classifier: Programming Language :: Python :: 3.8
Classifier: Programming Language :: Python :: 3.9
Classifier: Programming Language :: Python :: 3.10
Classifier: Programming Language :: Python :: 3.11
Requires-Dist: requests (>=2.31.0,<3.0.0)
Project-URL: Repository, https://github.com/Maglev-AI/MaglevAI
